boltzGUI/__init__.py
boltzGUI/boltzgui.py
boltzGUI/gather_energys.pl
boltzGUI/main.py
boltzGUI/version.py
btpgui-1.0.3.dist-info/METADATA
btpgui-1.0.3.dist-info/WHEEL
btpgui-1.0.3.dist-info/entry_points.txt
btpgui-1.0.3.dist-info/top_level.txt
btpgui-1.0.3.dist-info/RECORD
