Metadata-Version: 2.1
Name: btpgui
Version: 1.0.3
Summary: Interface graphic to BoltzTraP2
Home-page: https://github.com/ghlam14
Author: G. Benabdellah
Author-email: ghlam.benabdellah@gmail.com
Classifier: Programming Language :: Python :: 3
Classifier: License :: OSI Approved :: GNU General Public License v3 (GPLv3)
Classifier: Operating System :: OS Independent
Requires-Python: >=3.6
Requires-Dist: packaging
Requires-Dist: matplotlib
Requires-Dist: Pillow
Requires-Dist: tk
Requires-Dist: BoltZtraP2
